hydrating/__init__.py
hydrating/core/__init__.py
hydrating/core/grades.py
hydrating/core/hydrating.py
hydrating/models/__init__.py
hydrating/models/models.py
hydrating/models/rating_functions.py
hydrating-0.0.2.dist-info/LICENSE
hydrating-0.0.2.dist-info/METADATA
hydrating-0.0.2.dist-info/WHEEL
hydrating-0.0.2.dist-info/top_level.txt
hydrating-0.0.2.dist-info/RECORD
