Metadata-Version: 2.1
Name: hydrating
Version: 0.0.2
Summary: fitting hydrological stage discharge rating curves
Home-page: https://github.com/rhkarls/hydrating
License: MIT
Project-URL: Bug Tracker, https://github.com/rhkarls/hydrating/issues
Classifier: Development Status :: 2 - Pre-Alpha
Classifier: License :: OSI Approved :: MIT License
Classifier: Programming Language :: Python :: 3
Classifier: Programming Language :: Python :: 3.8
Classifier: Programming Language :: Python :: 3.9
Classifier: Programming Language :: Python :: 3.10
Classifier: Programming Language :: Python :: 3.11
Requires-Python: >=3.9
License-File: LICENSE
Requires-Dist: numpy
Requires-Dist: pandas
Requires-Dist: lmfit
Requires-Dist: matplotlib
Provides-Extra: test
Requires-Dist: pytest ; extra == 'test'
